LICENSE
MANIFEST.in
README.rst
setup.py
InteractiveCommandLine/HigherLevel.py
InteractiveCommandLine/__init__.py
InteractiveCommandLine.egg-info/PKG-INFO
InteractiveCommandLine.egg-info/SOURCES.txt
InteractiveCommandLine.egg-info/dependency_links.txt
InteractiveCommandLine.egg-info/requires.txt
InteractiveCommandLine.egg-info/top_level.txt
InteractiveCommandLine/Foundations/Commands.py
InteractiveCommandLine/Foundations/Options.py
InteractiveCommandLine/Foundations/Program.py
InteractiveCommandLine/Foundations/__init__.py
InteractiveCommandLine/tests/AllTests.py
InteractiveCommandLine/tests/AutoHelp.py
InteractiveCommandLine/tests/BasicCommandAndOptionHandling.py
InteractiveCommandLine/tests/Grouping.py
InteractiveCommandLine/tests/Misc.py
InteractiveCommandLine/tests/SimpleOptions.py
InteractiveCommandLine/tests/SubCommands.py
InteractiveCommandLine/tests/__init__.py
InteractiveCommandLine/tests/__main__.py