Metadata-Version: 1.1
Name: InteractiveCommandLine
Version: 0.3.1
Summary: Framework for interactive and command-line programs.
Home-page: http://pythonhosted.org/InteractiveCommandLine
Author: Vincent Jacques
Author-email: vincent@vincent-jacques.net
License: MIT
Platform: UNKNOWN
Classifier: Development Status :: 2 - Pre-Alpha
Classifier: Intended Audience :: Developers
Classifier: License :: OSI Approved
Classifier: License :: OSI Approved :: MIT License
Classifier: Operating System :: OS Independent
Classifier: Programming Language :: Python
Classifier: Programming Language :: Python :: 2
Classifier: Programming Language :: Python :: 2.7
Classifier: Programming Language :: Python :: 3
Classifier: Programming Language :: Python :: 3.3
Classifier: Programming Language :: Python :: 3.4
Classifier: Environment :: Console
